comfy/__init__.py
comfy/checkpoint_pickle.py
comfy/cli_args.py
comfy/cli_args_types.py
comfy/clip_config_bigg.json
comfy/clip_model.py
comfy/clip_vision.py
comfy/clip_vision_config_g.json
comfy/clip_vision_config_h.json
comfy/clip_vision_config_vitl.json
comfy/conds.py
comfy/controlnet.py
comfy/diffusers_convert.py
comfy/diffusers_load.py
comfy/digest.py
comfy/execution_context.py
comfy/gligen.py
comfy/images.py
comfy/interruption.py
comfy/latent_formats.py
comfy/lora.py
comfy/model_base.py
comfy/model_detection.py
comfy/model_downloader.py
comfy/model_downloader_types.py
comfy/model_management.py
comfy/model_management_types.py
comfy/model_patcher.py
comfy/model_sampling.py
comfy/node_helpers.py
comfy/open_exr.py
comfy/ops.py
comfy/options.py
comfy/package_data_path_helper.py
comfy/sample.py
comfy/sampler_helpers.py
comfy/sampler_names.py
comfy/samplers.py
comfy/sd.py
comfy/sd1_clip.py
comfy/sd1_clip_config.json
comfy/sd2_clip.py
comfy/sd2_clip_config.json
comfy/sd3_clip.py
comfy/sdxl_clip.py
comfy/supported_models.py
comfy/supported_models_base.py
comfy/t5.py
comfy/t5_config_base.json
comfy/t5_config_xxl.json
comfy/tracing_compatibility.py
comfy/types.py
comfy/utils.py
comfy/analytics/__init__.py
comfy/analytics/analytics.py
comfy/analytics/event_tracker.py
comfy/analytics/identity_provider_nt.py
comfy/analytics/multi_event_tracker.py
comfy/analytics/plausible.py
comfy/api/__init__.py
comfy/api/api_client.py
comfy/api/api_response.py
comfy/api/exceptions.py
comfy/api/openapi.yaml
comfy/api/openapi_python_config.yaml
comfy/api/py.typed
comfy/api/rest.py
comfy/api/security_schemes.py
comfy/api/server.py
comfy/api/apis/__init__.py
comfy/api/apis/path_to_api.py
comfy/api/apis/tag_to_api.py
comfy/api/apis/paths/__init__.py
comfy/api/apis/paths/api_v1_images_digest.py
comfy/api/apis/paths/api_v1_prompts.py
comfy/api/apis/paths/embeddings.py
comfy/api/apis/paths/extensions.py
comfy/api/apis/paths/history.py
comfy/api/apis/paths/interrupt.py
comfyui-0.0.1.dist-info/LICENSE
comfyui-0.0.1.dist-info/METADATA
comfyui-0.0.1.dist-info/WHEEL
comfyui-0.0.1.dist-info/entry_points.txt
comfyui-0.0.1.dist-info/top_level.txt
comfyui-0.0.1.dist-info/RECORD
