Metadata-Version: 2.1
Name: comfyui
Version: 0.0.1
Summary: An installable version of ComfyUI
Author: Contributors_of_ComfyUI
Requires-Python: >=3.10,<3.13
License-File: LICENSE
Requires-Dist: torch
Requires-Dist: torchvision
Requires-Dist: torchdiffeq >=0.2.3
Requires-Dist: torchsde >=0.2.6
Requires-Dist: einops >=0.6.0
Requires-Dist: open-clip-torch >=2.16.0
Requires-Dist: transformers >=4.29.1
Requires-Dist: peft
Requires-Dist: torchinfo
Requires-Dist: fschat[model_worker]
Requires-Dist: safetensors >=0.4.2
Requires-Dist: bitsandbytes
Requires-Dist: pytorch-lightning >=2.0.0
Requires-Dist: aiohttp >=3.8.4
Requires-Dist: accelerate >=0.25.0
Requires-Dist: pyyaml >=6.0
Requires-Dist: scikit-image >=0.20.0
Requires-Dist: jsonmerge >=1.9.0
Requires-Dist: clean-fid >=0.1.35
Requires-Dist: resize-right >=0.0.2
Requires-Dist: opencv-python-headless >=4.9.0.80
Requires-Dist: albumentations >=1.3.0
Requires-Dist: aiofiles >=23.1.0
Requires-Dist: frozendict >=2.3.6
Requires-Dist: python-dateutil >=2.8.2
Requires-Dist: importlib-resources
Requires-Dist: Pillow
Requires-Dist: scipy
Requires-Dist: tqdm
Requires-Dist: protobuf
Requires-Dist: psutil
Requires-Dist: ConfigArgParse
Requires-Dist: aio-pika
Requires-Dist: pyjwt[crypto]
Requires-Dist: kornia >=0.7.1
Requires-Dist: mpmath !=1.4.0a0,>=1.0
Requires-Dist: huggingface-hub
Requires-Dist: lazy-object-proxy
Requires-Dist: can-ada
Requires-Dist: fsspec
Requires-Dist: natsort
Requires-Dist: OpenEXR
Requires-Dist: opentelemetry-distro
Requires-Dist: opentelemetry-exporter-otlp
Requires-Dist: opentelemetry-propagator-jaeger
Requires-Dist: opentelemetry-instrumentation
Requires-Dist: opentelemetry-util-http
Requires-Dist: opentelemetry-instrumentation-aio-pika
Requires-Dist: opentelemetry-instrumentation-requests
Requires-Dist: opentelemetry-semantic-conventions
Requires-Dist: wrapt >=1.16.0
Requires-Dist: certifi
Requires-Dist: spandrel
Provides-Extra: dev
Requires-Dist: pytest ; extra == 'dev'
Requires-Dist: pytest-asyncio ; extra == 'dev'
Requires-Dist: websocket-client ==1.6.1 ; extra == 'dev'
Requires-Dist: PyInstaller ; extra == 'dev'
Requires-Dist: testcontainers ; extra == 'dev'
Requires-Dist: testcontainers-rabbitmq ; extra == 'dev'
Requires-Dist: mypy >=1.6.0 ; extra == 'dev'
Requires-Dist: freezegun ; extra == 'dev'
Requires-Dist: coverage ; extra == 'dev'
